{
  "id": "2a2eb1f0-a221-49c1-b63f-c5acde03f6b3",
  "prevId": "67bcc439-4a7d-42f6-b41a-3a670bbd665e",
  "version": "7",
  "dialect": "postgresql",
  "tables": {
    "public.activity_logs": {
      "name": "activity_logs",
      "schema": "",
      "columns": {
        "id": {
          "name": "id",
          "type": "serial",
          "primaryKey": true,
          "notNull": true
        },
        "applicationId": {
          "name": "applicationId",
          "type": "integer",
          "primaryKey": false,
          "notNull": true
        },
        "staffId": {
          "name": "staffId",
          "type": "integer",
          "primaryKey": false,
          "notNull": true
        },
        "staffName": {
          "name": "staffName",
          "type": "varchar(255)",
          "primaryKey": false,
          "notNull": true
        },
        "staffEmail": {
          "name": "staffEmail",
          "type": "varchar(320)",
          "primaryKey": false,
          "notNull": true
        },
        "action": {
          "name": "action",
          "type": "activity_action",
          "typeSchema": "public",
          "primaryKey": false,
          "notNull": true
        },
        "remarks": {
          "name": "remarks",
          "type": "text",
          "primaryKey": false,
          "notNull": false
        },
        "createdAt": {
          "name": "createdAt",
          "type": "timestamp",
          "primaryKey": false,
          "notNull": true,
          "default": "now()"
        }
      },
      "indexes": {},
      "foreignKeys": {},
      "compositePrimaryKeys": {},
      "uniqueConstraints": {},
      "policies": {},
      "checkConstraints": {},
      "isRLSEnabled": false
    },
    "public.applications": {
      "name": "applications",
      "schema": "",
      "columns": {
        "id": {
          "name": "id",
          "type": "serial",
          "primaryKey": true,
          "notNull": true
        },
        "referenceNumber": {
          "name": "referenceNumber",
          "type": "varchar(32)",
          "primaryKey": false,
          "notNull": true
        },
        "applicantName": {
          "name": "applicantName",
          "type": "varchar(255)",
          "primaryKey": false,
          "notNull": true
        },
        "applicantEmail": {
          "name": "applicantEmail",
          "type": "varchar(320)",
          "primaryKey": false,
          "notNull": true
        },
        "applicantPhone": {
          "name": "applicantPhone",
          "type": "varchar(20)",
          "primaryKey": false,
          "notNull": true
        },
        "applicantCapacity": {
          "name": "applicantCapacity",
          "type": "varchar(100)",
          "primaryKey": false,
          "notNull": true
        },
        "barangay": {
          "name": "barangay",
          "type": "varchar(100)",
          "primaryKey": false,
          "notNull": true
        },
        "propertyLocation": {
          "name": "propertyLocation",
          "type": "text",
          "primaryKey": false,
          "notNull": true
        },
        "propertyAddress": {
          "name": "propertyAddress",
          "type": "text",
          "primaryKey": false,
          "notNull": true
        },
        "projectType": {
          "name": "projectType",
          "type": "varchar(100)",
          "primaryKey": false,
          "notNull": true
        },
        "projectScope": {
          "name": "projectScope",
          "type": "text",
          "primaryKey": false,
          "notNull": true
        },
        "estimatedCost": {
          "name": "estimatedCost",
          "type": "numeric(12, 2)",
          "primaryKey": false,
          "notNull": false
        },
        "attachments": {
          "name": "attachments",
          "type": "jsonb",
          "primaryKey": false,
          "notNull": false
        },
        "status": {
          "name": "status",
          "type": "application_status",
          "typeSchema": "public",
          "primaryKey": false,
          "notNull": true,
          "default": "'pending'"
        },
        "submittedAt": {
          "name": "submittedAt",
          "type": "timestamp",
          "primaryKey": false,
          "notNull": true,
          "default": "now()"
        },
        "processedAt": {
          "name": "processedAt",
          "type": "timestamp",
          "primaryKey": false,
          "notNull": false
        },
        "staffRemarks": {
          "name": "staffRemarks",
          "type": "text",
          "primaryKey": false,
          "notNull": false
        },
        "createdAt": {
          "name": "createdAt",
          "type": "timestamp",
          "primaryKey": false,
          "notNull": true,
          "default": "now()"
        },
        "updatedAt": {
          "name": "updatedAt",
          "type": "timestamp",
          "primaryKey": false,
          "notNull": true,
          "default": "now()"
        }
      },
      "indexes": {},
      "foreignKeys": {},
      "compositePrimaryKeys": {},
      "uniqueConstraints": {
        "applications_referenceNumber_unique": {
          "name": "applications_referenceNumber_unique",
          "nullsNotDistinct": false,
          "columns": [
            "referenceNumber"
          ]
        }
      },
      "policies": {},
      "checkConstraints": {},
      "isRLSEnabled": false
    },
    "public.notifications": {
      "name": "notifications",
      "schema": "",
      "columns": {
        "id": {
          "name": "id",
          "type": "serial",
          "primaryKey": true,
          "notNull": true
        },
        "applicationId": {
          "name": "applicationId",
          "type": "integer",
          "primaryKey": false,
          "notNull": true
        },
        "recipientEmail": {
          "name": "recipientEmail",
          "type": "varchar(320)",
          "primaryKey": false,
          "notNull": true
        },
        "type": {
          "name": "type",
          "type": "notification_type",
          "typeSchema": "public",
          "primaryKey": false,
          "notNull": true
        },
        "subject": {
          "name": "subject",
          "type": "varchar(255)",
          "primaryKey": false,
          "notNull": true
        },
        "body": {
          "name": "body",
          "type": "text",
          "primaryKey": false,
          "notNull": true
        },
        "sent": {
          "name": "sent",
          "type": "boolean",
          "primaryKey": false,
          "notNull": true,
          "default": false
        },
        "sentAt": {
          "name": "sentAt",
          "type": "timestamp",
          "primaryKey": false,
          "notNull": false
        },
        "deliveryStatus": {
          "name": "deliveryStatus",
          "type": "delivery_status",
          "typeSchema": "public",
          "primaryKey": false,
          "notNull": true,
          "default": "'pending'"
        },
        "createdAt": {
          "name": "createdAt",
          "type": "timestamp",
          "primaryKey": false,
          "notNull": true,
          "default": "now()"
        },
        "updatedAt": {
          "name": "updatedAt",
          "type": "timestamp",
          "primaryKey": false,
          "notNull": true,
          "default": "now()"
        }
      },
      "indexes": {},
      "foreignKeys": {},
      "compositePrimaryKeys": {},
      "uniqueConstraints": {},
      "policies": {},
      "checkConstraints": {},
      "isRLSEnabled": false
    },
    "public.users": {
      "name": "users",
      "schema": "",
      "columns": {
        "id": {
          "name": "id",
          "type": "serial",
          "primaryKey": true,
          "notNull": true
        },
        "openId": {
          "name": "openId",
          "type": "varchar(64)",
          "primaryKey": false,
          "notNull": true
        },
        "name": {
          "name": "name",
          "type": "text",
          "primaryKey": false,
          "notNull": false
        },
        "email": {
          "name": "email",
          "type": "varchar(320)",
          "primaryKey": false,
          "notNull": false
        },
        "loginMethod": {
          "name": "loginMethod",
          "type": "varchar(64)",
          "primaryKey": false,
          "notNull": false
        },
        "role": {
          "name": "role",
          "type": "role",
          "typeSchema": "public",
          "primaryKey": false,
          "notNull": true,
          "default": "'user'"
        },
        "createdAt": {
          "name": "createdAt",
          "type": "timestamp",
          "primaryKey": false,
          "notNull": true,
          "default": "now()"
        },
        "updatedAt": {
          "name": "updatedAt",
          "type": "timestamp",
          "primaryKey": false,
          "notNull": true,
          "default": "now()"
        },
        "lastSignedIn": {
          "name": "lastSignedIn",
          "type": "timestamp",
          "primaryKey": false,
          "notNull": true,
          "default": "now()"
        }
      },
      "indexes": {},
      "foreignKeys": {},
      "compositePrimaryKeys": {},
      "uniqueConstraints": {
        "users_openId_unique": {
          "name": "users_openId_unique",
          "nullsNotDistinct": false,
          "columns": [
            "openId"
          ]
        }
      },
      "policies": {},
      "checkConstraints": {},
      "isRLSEnabled": false
    }
  },
  "enums": {
    "public.activity_action": {
      "name": "activity_action",
      "schema": "public",
      "values": [
        "submitted",
        "approved",
        "on_hold",
        "resubmission_requested",
        "viewed"
      ]
    },
    "public.application_status": {
      "name": "application_status",
      "schema": "public",
      "values": [
        "pending",
        "approved",
        "for_resubmission",
        "on_hold"
      ]
    },
    "public.delivery_status": {
      "name": "delivery_status",
      "schema": "public",
      "values": [
        "pending",
        "sent",
        "failed",
        "bounced"
      ]
    },
    "public.notification_type": {
      "name": "notification_type",
      "schema": "public",
      "values": [
        "submitted",
        "approved",
        "on_hold",
        "resubmission_requested"
      ]
    },
    "public.role": {
      "name": "role",
      "schema": "public",
      "values": [
        "user",
        "admin",
        "staff"
      ]
    }
  },
  "schemas": {},
  "sequences": {},
  "roles": {},
  "policies": {},
  "views": {},
  "_meta": {
    "columns": {},
    "schemas": {},
    "tables": {}
  }
}